torchfast/__init__.py
torchfast/callbacks/__init__.py
torchfast/callbacks/callbacks.py
torchfast/data/__init__.py
torchfast/data/lmdbdict.py
torchfast/data/sampler.py
torchfast/data/tensor_dataloader.py
torchfast/learner/__init__.py
torchfast/learner/layer.py
torchfast/learner/learner.py
torchfast/learner/skwrapper.py
torchfast/loss/__init__.py
torchfast/loss/loss.py
torchfast/metrics/__init__.py
torchfast/metrics/functional.py
torchfast/metrics/metrics.py
torchfast/misc/__init__.py
torchfast/misc/kmeans.py
torchfast/misc/misc.py
torchfast/misc/parallel.py
torchfast/optimizer/__init__.py
torchfast/optimizer/optimizer.py
Torchfast-1.1.2.dist-info/LICENSE
Torchfast-1.1.2.dist-info/METADATA
Torchfast-1.1.2.dist-info/WHEEL
Torchfast-1.1.2.dist-info/top_level.txt
Torchfast-1.1.2.dist-info/RECORD
